migratory/__init__.py
migratory/migration.py
migratory/settings.py
migratory-0.2.0.dist-info/METADATA
migratory-0.2.0.dist-info/WHEEL
migratory-0.2.0.dist-info/RECORD
